onqlclient/__init__.py
onql_client-0.1.2.dist-info/METADATA
onql_client-0.1.2.dist-info/WHEEL
onql_client-0.1.2.dist-info/top_level.txt
onql_client-0.1.2.dist-info/RECORD
