Metadata-Version: 2.4
Name: onql-client
Version: 0.1.2
Summary: ONQL Python client
Home-page: https://onql.org
Author: Paras Virk
Author-email: Paras Virk <team@autobit.co>
License: MIT
Project-URL: Homepage, https://onql.org
Requires-Python: >=3.7
Dynamic: author
Dynamic: home-page
Dynamic: requires-python
